{"ticker": "EICHERMOT.NS", "cached_at": "2025-11-27T18:02:32.188648", "signals": {"ticker": "EICHERMOT.NS", "current_price": 6999.0, "timestamp": "2025-11-27T18:02:32.188648", "overall_signal": {"signal": "BUY", "score": 68.38, "color": "green", "confidence": "Medium-High", "strength": "Medium"}, "technical_analysis": {"score": 72.5, "signals": [{"name": "RSI", "score": 50, "weight": 20}, {"name": "MACD", "score": 85.0, "weight": 20}, {"name": "Bollinger Bands", "score": 50, "weight": 15}, {"name": "Moving Averages", "score": 85.0, "weight": 15}, {"name": "Volume", "score": 50, "weight": 10}, {"name": "Momentum", "score": 75, "weight": 20}]}, "fundamental_analysis": {"score": 73.75, "signals": [{"name": "P/E Ratio", "score": 25, "weight": 25}, {"name": "P/B Ratio", "score": 50, "weight": 15}, {"name": "ROE", "score": 85.0, "weight": 20}, {"name": "Debt/Equity", "score": 85.0, "weight": 20}, {"name": "Profit Margin", "score": 85.0, "weight": 20}], "sector": "Automobile"}, "sentiment_score": 50, "timeframe_signals": {"intraday": {"timeframe": "1-3 Days", "signal": "SELL", "score": 30, "description": "Short-term scalping and day trading"}, "swing": {"timeframe": "1-4 Weeks", "signal": "BUY", "score": 85.0, "description": "Medium-term swing trading"}, "long_term": {"timeframe": "3-12 Months", "signal": "BUY", "score": 85.0, "description": "Long-term position trading"}}, "vwap_strategy": {"signal": "NEUTRAL", "score": 60, "effectiveness": "EXCELLENT (70-76% win rate)", "recommendation": "Use this strategy - Perfect for intraday trading", "vwap_data": {"vwap": 6966.259117612821, "upper_band_1": 7108.033263262339, "lower_band_1": 6824.484971963303, "upper_band_2": 7249.807408911856, "lower_band_2": 6682.710826313785, "upper_band_3": 7391.581554561374, "lower_band_3": 6540.936680664267, "position": "Above VWAP", "position_score": 60, "distance_from_vwap_percent": 0.4699923134412316}, "price_action": {"patterns": ["Three Black Crows"], "signal_strength": -35, "dominant_pattern": "BEARISH"}, "confirmations": 0.0, "timeframe_suitability": {"intraday": "\u2705 EXCELLENT (70-76% win rate)", "day_trading": "\u26a0\ufe0f MODERATE (65-70% win rate)", "swing": "\u274c NOT RECOMMENDED - Use MACD + EMA instead", "long_term": "\u274c NOT RECOMMENDED - Use Fundamental Analysis instead"}, "strength": "Weak"}, "key_indicators": {"rsi": 51.52, "macd_histogram": 23.8386, "price_vs_sma50": "Above", "price_vs_sma200": "Above", "volume_ratio": 0.87, "adx": 27.29, "atr": 145.0714}, "confidence_level": "Medium", "signal_conflicts": {"has_conflicts": true, "conflict_count": 1, "conflicts": ["\u26a0\ufe0f CONFLICT: Short-term bearish but long-term bullish - May be healthy pullback in uptrend"], "priority": {"has_conflicts": true, "recommendations": [{"trading_style": "Intraday/Day Trading", "priority_signal": "NEUTRAL", "priority_score": 60, "reason": "VWAP strategy has 70-76% historical win rate for intraday, prioritize it over other signals", "action": "Follow VWAP signal, ignore conflicting intraday signal"}, {"trading_style": "Swing Trading (1-4 weeks)", "priority_signal": "BUY", "priority_score": 85.0, "reason": "Swing signal uses multi-indicator confluence over 50 days", "action": "Follow swing signal for 1-4 week holds"}, {"trading_style": "Long-term Investing (3-12 months)", "priority_signal": "BUY", "priority_score": 85.0, "reason": "Long-term signal focuses on trend following with 200-day MA", "action": "Follow long-term signal, ignore short-term noise"}]}}, "risk_management": {"stop_loss": 6708.86, "take_profit": 7724.36, "stop_loss_pct": 4.15, "take_profit_pct": 10.36, "position_size_pct": 3.0, "risk_reward_ratio": 2.5, "recommendation": "\u2705 Risk $4.1% to make $10.4% | Position: 3.0% of portfolio"}, "trading_recommendation": {"recommendation": "\u2705 STRONG TRADE - High confidence, good setup", "safety_level": "SAFE", "confidence": "Medium"}}}